{
  "annotations": {
    "list": [
      {
        "builtIn": 1,
        "datasource": {
          "type": "grafana",
          "uid": "-- Grafana --"
        },
        "enable": true,
        "hide": true,
        "iconColor": "rgba(0, 211, 255, 1)",
        "name": "Annotations & Alerts",
        "type": "dashboard"
      }
    ]
  },
  "editable": true,
  "fiscalYearStartMonth": 0,
  "graphTooltip": 0,
  "links": [],
  "panels": [
    {
      "collapsed": false,
      "gridPos": {
        "h": 1,
        "w": 24,
        "x": 0,
        "y": 0
      },
      "id": 2,
      "panels": [],
      "title": "Hardware Monitoring",
      "type": "row"
    },
    {
      "datasource": {
        "type": "prometheus",
        "uid": "dfhwt9oo4ay9sb"
      },
      "fieldConfig": {
        "defaults": {
          "color": {
            "mode": "palette-classic"
          },
          "custom": {
            "axisBorderShow": false,
            "axisCenteredZero": false,
            "axisColorMode": "text",
            "axisLabel": "% of one core",
            "axisPlacement": "auto",
            "barAlignment": 0,
            "barWidthFactor": 0.6,
            "drawStyle": "line",
            "fillOpacity": 0,
            "gradientMode": "none",
            "hideFrom": {
              "legend": false,
              "tooltip": false,
              "viz": false
            },
            "insertNulls": false,
            "lineInterpolation": "linear",
            "lineWidth": 1,
            "pointSize": 5,
            "scaleDistribution": {
              "type": "linear"
            },
            "showPoints": "auto",
            "showValues": false,
            "spanNulls": false,
            "stacking": {
              "group": "A",
              "mode": "none"
            },
            "thresholdsStyle": {
              "mode": "off"
            }
          },
          "mappings": [],
          "thresholds": {
            "mode": "absolute",
            "steps": [
              {
                "color": "green",
                "value": 0
              },
              {
                "color": "red",
                "value": 90
              }
            ]
          }
        },
        "overrides": []
      },
      "gridPos": {
        "h": 11,
        "w": 10,
        "x": 0,
        "y": 1
      },
      "id": 1,
      "options": {
        "legend": {
          "calcs": [],
          "displayMode": "list",
          "placement": "bottom",
          "showLegend": true
        },
        "tooltip": {
          "hideZeros": false,
          "mode": "single",
          "sort": "none"
        }
      },
      "pluginVersion": "12.4.2",
      "targets": [
        {
          "datasource": {
            "type": "prometheus",
            "uid": "dfhwt9oo4ay9sb"
          },
          "editorMode": "code",
          "exemplar": false,
          "expr": "sum by (name) (\n  rate(container_cpu_usage_seconds_total{name=~\"anizenith_(frontend|backend)\"}[5m])\n) * 100",
          "format": "time_series",
          "instant": false,
          "legendFormat": "{{name}}",
          "range": true,
          "refId": "CPU Utilization query"
        }
      ],
      "title": "CPU Utilization",
      "type": "timeseries"
    },
    {
      "datasource": {
        "type": "prometheus",
        "uid": "dfhwt9oo4ay9sb"
      },
      "fieldConfig": {
        "defaults": {
          "color": {
            "mode": "palette-classic"
          },
          "custom": {
            "axisBorderShow": false,
            "axisCenteredZero": false,
            "axisColorMode": "text",
            "axisLabel": "Memory in GB",
            "axisPlacement": "auto",
            "barAlignment": 0,
            "barWidthFactor": 0.6,
            "drawStyle": "line",
            "fillOpacity": 0,
            "gradientMode": "none",
            "hideFrom": {
              "legend": false,
              "tooltip": false,
              "viz": false
            },
            "insertNulls": false,
            "lineInterpolation": "linear",
            "lineWidth": 1,
            "pointSize": 5,
            "scaleDistribution": {
              "type": "linear"
            },
            "showPoints": "auto",
            "showValues": false,
            "spanNulls": false,
            "stacking": {
              "group": "A",
              "mode": "none"
            },
            "thresholdsStyle": {
              "mode": "off"
            }
          },
          "mappings": [],
          "thresholds": {
            "mode": "absolute",
            "steps": [
              {
                "color": "green",
                "value": 0
              },
              {
                "color": "red",
                "value": 90
              }
            ]
          }
        },
        "overrides": []
      },
      "gridPos": {
        "h": 11,
        "w": 11,
        "x": 10,
        "y": 1
      },
      "id": 3,
      "options": {
        "legend": {
          "calcs": [],
          "displayMode": "list",
          "placement": "bottom",
          "showLegend": true
        },
        "tooltip": {
          "hideZeros": false,
          "mode": "single",
          "sort": "none"
        }
      },
      "pluginVersion": "12.4.2",
      "targets": [
        {
          "datasource": {
            "type": "prometheus",
            "uid": "dfhwt9oo4ay9sb"
          },
          "editorMode": "code",
          "exemplar": false,
          "expr": "sum by (name) (\n  container_memory_usage_bytes{name=~\"anizenith_(frontend|backend)\"}\n) / (1024 * 1024 * 1024)",
          "format": "time_series",
          "instant": false,
          "legendFormat": "{{name}}",
          "range": true,
          "refId": "Memory Utilization query"
        }
      ],
      "title": "Memory Utilization",
      "type": "timeseries"
    }
  ],
  "preload": false,
  "schemaVersion": 42,
  "tags": [],
  "templating": {
    "list": []
  },
  "time": {
    "from": "now-30m",
    "to": "now"
  },
  "timepicker": {},
  "timezone": "browser",
  "title": "AniZenith Monitoring Dashboard",
  "uid": "ad9gktj",
  "version": 4,
  "weekStart": ""
}